eval/__init__.py
eval/browsecomp_eval.py
eval/common.py
eval/custom_conversation_evaluator.py
eval/download_healthbench_dataset.py
eval/drop_eval.py
eval/eval_types.py
eval/evaluate_appointment_conversation.py
eval/evaluate_conversation.py
eval/evaluate_from_file.py
eval/evaluate_my_conversation.py
eval/example_whispey_healthbench.py
eval/fast_healthbench_eval.py
eval/gpqa_eval.py
eval/healthbench_eval.py
eval/healthbench_eval_test.py
eval/healthbench_meta_eval.py
eval/healthbench_meta_eval_test.py
eval/humaneval_eval.py
eval/math_eval.py
eval/mgsm_eval.py
eval/mmlu_eval.py
eval/run_multilingual_mmlu.py
eval/simple_evals.py
eval/simple_healthbench_eval.py
eval/simpleqa_eval.py
eval/ultra_fast_healthbench.py
eval/sampler/__init__.py
eval/sampler/chat_completion_sampler.py
eval/sampler/claude_sampler.py
eval/sampler/o_chat_completion_sampler.py
eval/sampler/responses_sampler.py
whispey/__init__.py
whispey/event_handlers.py
whispey/metrics_service.py
whispey/pricing_calculator.py
whispey/send_log.py
whispey/whispey.py
whispey-4.1.5.dist-info/METADATA
whispey-4.1.5.dist-info/WHEEL
whispey-4.1.5.dist-info/top_level.txt
whispey-4.1.5.dist-info/RECORD
