Metadata-Version: 2.4
Name: Whispey
Version: 4.1.5
Summary: Voice Analytics SDK for AI Agents
Home-page: https://whispey.xyz/
Author: Whispey AI Voice Analytics
Author-email: Pype AI Voice Analytics <support@pype.ai>
License: MIT
Project-URL: Homepage, https://pype.ai
Project-URL: Repository, https://github.com/PYPE-AI-MAIN/whispey
Project-URL: Documentation, https://docs.pype.ai
Keywords: voice analytics,AI agents,conversation intelligence,pype
Classifier: Development Status :: 5 - Production/Stable
Classifier: Intended Audience :: Developers
Classifier: License :: OSI Approved :: MIT License
Classifier: Programming Language :: Python :: 3
Classifier: Programming Language :: Python :: 3.8
Classifier: Programming Language :: Python :: 3.9
Classifier: Programming Language :: Python :: 3.10
Classifier: Programming Language :: Python :: 3.11
Classifier: Programming Language :: Python :: 3.12
Requires-Python: >=3.8
Requires-Dist: livekit-agents>=1.2.2
Requires-Dist: aiohttp>=3.8.0
Requires-Dist: python-dotenv>=1.0.0
Dynamic: author
Dynamic: home-page
Dynamic: requires-python
